cpt_python/__init__.py
cpt_python/__main__.py
cpt_python/blemanager.py
cpt_python/bluetooth_data/__init__.py
cpt_python/bluetooth_data/advertising_data.py
cpt_python/bluetooth_data/battery_status_virtual_sensors.py
cpt_python/bluetooth_data/mode_id.py
cpt_python/bluetooth_data/prediction_status.py
cpt_python/bluetooth_data/probe_status.py
cpt_python/bluetooth_data/probe_temperatures.py
cpt_python/bluetooth_data/virtual_sensors.py
combustion_predictive_thermometer_python-0.0.1.dist-info/METADATA
combustion_predictive_thermometer_python-0.0.1.dist-info/WHEEL
combustion_predictive_thermometer_python-0.0.1.dist-info/top_level.txt
combustion_predictive_thermometer_python-0.0.1.dist-info/RECORD
